pyrchive.py
pyrchive-0.0.1.dist-info/LICENSE
pyrchive-0.0.1.dist-info/WHEEL
pyrchive-0.0.1.dist-info/METADATA
pyrchive-0.0.1.dist-info/RECORD
